meltdown/HtmlProducer.py
meltdown/MarkdownParser.py
meltdown/Nodes.py
meltdown/__init__.py
meltdown-0.0.6.dist-info/WHEEL
meltdown-0.0.6.dist-info/METADATA
meltdown-0.0.6.dist-info/RECORD
