Metadata-Version: 2.3
Name: meltdown
Version: 0.0.6
Summary: A markdown parser
Author: flofriday
Author-email: flofriday <flohacksfriday@gmail.com>
Classifier: Programming Language :: Python :: 3
Classifier: License :: OSI Approved :: MIT License
Classifier: Operating System :: OS Independent
Requires-Python: >=3.12
Project-URL: Homepage, https://github.com/flofriday/meltdown
Project-URL: Issues, https://github.com/flofriday/meltdown/issues
